README.md
setup.py
dspca/__init__.py
dspca/dspca.py
dspca/utils.py
dspca.egg-info/PKG-INFO
dspca.egg-info/SOURCES.txt
dspca.egg-info/dependency_links.txt
dspca.egg-info/requires.txt
dspca.egg-info/top_level.txt