Metadata-Version: 2.1
Name: dspca
Version: 1.0.2
Summary: Demixed subspace principal component analysis (dsPCA)
Home-page: http://github.com/ryhattori/dspca
Author: Ryoma Hattori
Author-email: rhattori0204@gmail.com
License: MIT License
Platform: UNKNOWN
